pytest_lazy_fixtures/__init__.py
pytest_lazy_fixtures/fixture_collector.py
pytest_lazy_fixtures/lazy_fixture.py
pytest_lazy_fixtures/lazy_fixture_callable.py
pytest_lazy_fixtures/loader.py
pytest_lazy_fixtures/normalizer.py
pytest_lazy_fixtures/plugin.py
pytest_lazy_fixtures/py.typed
pytest_lazy_fixtures/utils.py
pytest_lazy_fixtures-1.3.3.dist-info/METADATA
pytest_lazy_fixtures-1.3.3.dist-info/WHEEL
pytest_lazy_fixtures-1.3.3.dist-info/entry_points.txt
pytest_lazy_fixtures-1.3.3.dist-info/licenses/LICENSE
pytest_lazy_fixtures-1.3.3.dist-info/RECORD
