Metadata-Version: 2.4
Name: pytest-lazy-fixtures
Version: 1.3.3
Summary: Allows you to use fixtures in @pytest.mark.parametrize.
Project-URL: Homepage, https://github.com/dev-petrov/pytest-lazy-fixtures
Project-URL: Repository, https://github.com/dev-petrov/pytest-lazy-fixtures
Author-email: Petrov Anton <antonp2@yandex.ru>
License-Expression: MIT
License-File: LICENSE
Keywords: fixture,lazy,pytest,tests
Requires-Python: >=3.8
Requires-Dist: pytest>=7
